CellularAutomaton/__init__.py
CellularAutomaton/automaton.py
CellularAutomaton/main.py
CellularAutomaton/visualize.py
2D_cellular_automaton-0.0.1.dist-info/LICENSE.txt
2D_cellular_automaton-0.0.1.dist-info/METADATA
2D_cellular_automaton-0.0.1.dist-info/WHEEL
2D_cellular_automaton-0.0.1.dist-info/top_level.txt
2D_cellular_automaton-0.0.1.dist-info/RECORD
