Metadata-Version: 2.1
Name: 2D-cellular-automaton
Version: 0.0.1
Summary: A package to visualize elementary 2D cellular automata with multiple starting indicies
Author-email: Muhammad Mir <mmir@drew.edu>
License: MIT License
Project-URL: repository, https://github.com/muhammadmir/2D-cellular-automaton
Keywords: Cellular Automata,Cellular Automaton
Classifier: Programming Language :: Python :: 3
Classifier: License :: OSI Approved :: MIT License
Classifier: Operating System :: OS Independent
Requires-Python: >=3.7
License-File: LICENSE.txt
Requires-Dist: bitarray (>=2.6.1)
Requires-Dist: Pillow
